Workbook

Sheet Summary
A1: Master-in-Equity sales — summary
A2: All figures are formulas over the "All cases" sheet; re-run the crawler and paste new rows there.
A4: County | B4: Cases | C4: Scheduled | D4: Cancelled / withdrawn | E4: Deficiency demanded | F4: Deficiency waived | G4: With judgment $ | H4: Total judgment $ (scheduled) | I4: With FMV
A5: Charleston | B5: =COUNTIF('All cases'!$A:$A,A5) | C5: =COUNTIFS('All cases'!$A:$A,A5,'All cases'!$E:$E,"scheduled") | D5: =B5-C5 | E5: =COUNTIFS('All cases'!$A:$A,A5,'All cases'!$J:$J,"demanded") | F5: =COUNTIFS('All cases'!$A:$A,A5,'All cases'!$J:$J,"waived") | G5: =COUNTIFS('All cases'!$A:$A,A5,'All cases'!$K:$K,">0") | H5: =SUMIFS('All cases'!$K:$K,'All cases'!$A:$A,A5,'All cases'!$E:$E,"scheduled") | I5: =COUNTIFS('All cases'!$A:$A,A5,'All cases'!$Q:$Q,">0")
A6: Georgetown | B6: =COUNTIF('All cases'!$A:$A,A6) | C6: =COUNTIFS('All cases'!$A:$A,A6,'All cases'!$E:$E,"scheduled") | D6: =B6-C6 | E6: =COUNTIFS('All cases'!$A:$A,A6,'All cases'!$J:$J,"demanded") | F6: =COUNTIFS('All cases'!$A:$A,A6,'All cases'!$J:$J,"waived") | G6: =COUNTIFS('All cases'!$A:$A,A6,'All cases'!$K:$K,">0") | H6: =SUMIFS('All cases'!$K:$K,'All cases'!$A:$A,A6,'All cases'!$E:$E,"scheduled") | I6: =COUNTIFS('All cases'!$A:$A,A6,'All cases'!$Q:$Q,">0")
A7: Greenville | B7: =COUNTIF('All cases'!$A:$A,A7) | C7: =COUNTIFS('All cases'!$A:$A,A7,'All cases'!$E:$E,"scheduled") | D7: =B7-C7 | E7: =COUNTIFS('All cases'!$A:$A,A7,'All cases'!$J:$J,"demanded") | F7: =COUNTIFS('All cases'!$A:$A,A7,'All cases'!$J:$J,"waived") | G7: =COUNTIFS('All cases'!$A:$A,A7,'All cases'!$K:$K,">0") | H7: =SUMIFS('All cases'!$K:$K,'All cases'!$A:$A,A7,'All cases'!$E:$E,"scheduled") | I7: =COUNTIFS('All cases'!$A:$A,A7,'All cases'!$Q:$Q,">0")
A8: Horry | B8: =COUNTIF('All cases'!$A:$A,A8) | C8: =COUNTIFS('All cases'!$A:$A,A8,'All cases'!$E:$E,"scheduled") | D8: =B8-C8 | E8: =COUNTIFS('All cases'!$A:$A,A8,'All cases'!$J:$J,"demanded") | F8: =COUNTIFS('All cases'!$A:$A,A8,'All cases'!$J:$J,"waived") | G8: =COUNTIFS('All cases'!$A:$A,A8,'All cases'!$K:$K,">0") | H8: =SUMIFS('All cases'!$K:$K,'All cases'!$A:$A,A8,'All cases'!$E:$E,"scheduled") | I8: =COUNTIFS('All cases'!$A:$A,A8,'All cases'!$Q:$Q,">0")
A9: Pickens | B9: =COUNTIF('All cases'!$A:$A,A9) | C9: =COUNTIFS('All cases'!$A:$A,A9,'All cases'!$E:$E,"scheduled") | D9: =B9-C9 | E9: =COUNTIFS('All cases'!$A:$A,A9,'All cases'!$J:$J,"demanded") | F9: =COUNTIFS('All cases'!$A:$A,A9,'All cases'!$J:$J,"waived") | G9: =COUNTIFS('All cases'!$A:$A,A9,'All cases'!$K:$K,">0") | H9: =SUMIFS('All cases'!$K:$K,'All cases'!$A:$A,A9,'All cases'!$E:$E,"scheduled") | I9: =COUNTIFS('All cases'!$A:$A,A9,'All cases'!$Q:$Q,">0")
A10: Spartanburg | B10: =COUNTIF('All cases'!$A:$A,A10) | C10: =COUNTIFS('All cases'!$A:$A,A10,'All cases'!$E:$E,"scheduled") | D10: =B10-C10 | E10: =COUNTIFS('All cases'!$A:$A,A10,'All cases'!$J:$J,"demanded") | F10: =COUNTIFS('All cases'!$A:$A,A10,'All cases'!$J:$J,"waived") | G10: =COUNTIFS('All cases'!$A:$A,A10,'All cases'!$K:$K,">0") | H10: =SUMIFS('All cases'!$K:$K,'All cases'!$A:$A,A10,'All cases'!$E:$E,"scheduled") | I10: =COUNTIFS('All cases'!$A:$A,A10,'All cases'!$Q:$Q,">0")
A11: Total | B11: =SUM(B5:B10) | C11: =SUM(C5:C10) | D11: =SUM(D5:D10) | E11: =SUM(E5:E10) | F11: =SUM(F5:F10) | G11: =SUM(G5:G10) | H11: =SUM(H5:H10) | I11: =SUM(I5:I10)

Sheet All cases
A1: County | B1: Sale date | C1: Sale # | D1: Case # | E1: Status | F1: Address | G1: TMS | H1: Plaintiff | I1: Defendant | J1: Deficiency | K1: Judgment $ | L1: As of | M1: Per diem $ | N1: Days to sale | O1: Est. owed sale day $ | P1: Interest | Q1: County FMV $ | R1: Debt ÷ FMV | S1: Acreage | T1: Land use / type | U1: Year built | V1: Sq ft | W1: Record owner | X1: Last sale | Y1: Order / judgment | Z1: Notice | AA1: Docket | AB1: Property card | AC1: Write-up
A2: Georgetown | B2: 46273 | D2: 2026-CP-22-00295 | E2: cancelled | F2: 1105 Merriman Rd., Georgetown, SC | G2: 05-0003-012-00-00 | H2: U. S. Bank Trust Comp. | I2: Brownstone Prop. | J2: demanded | N2: =IF(OR(B2="",L2=""),"",MAX(0,B2-L2)) | O2: =IF(K2="","",K2+IF(OR(M2="",N2=""),0,M2*N2)) | R2: =IF(OR(Q2="",Q2=0,O2=""),"",O2/Q2) | AC2: 1105 Merriman Rd., Georgetown, SC. Judgment $ not pulled yet (needs the PC run). DEFICIENCY DEMANDED — open 30 days. STATUS: CANCELLED.
A3: Georgetown | B3: 46273 | D3: 2025-CP-22-01076 | E3: scheduled | F3: 83 Polan Lane Georgetown, SC | G3: 03-0439-025-01-00 | H3: Howard and Howard | I3: Est. Bobbie Cuttino | J3: waived | N3: =IF(OR(B3="",L3=""),"",MAX(0,B3-L3)) | O3: =IF(K3="","",K3+IF(OR(M3="",N3=""),0,M3*N3)) | R3: =IF(OR(Q3="",Q3=0,O3=""),"",O3/Q3) | AC3: 83 Polan Lane Georgetown, SC. Judgment $ not pulled yet (needs the PC run). Deficiency waived — final on the day.
A4: Georgetown | B4: 46273 | D4: 2026-CP-22-00122 | E4: scheduled | F4: 1832 Middleton St., Georgetown, SC | G4: 02-0107-141-00-00 | H4: SouthState Bank | I4: Roland Floyd | J4: waived | N4: =IF(OR(B4="",L4=""),"",MAX(0,B4-L4)) | O4: =IF(K4="","",K4+IF(OR(M4="",N4=""),0,M4*N4)) | R4: =IF(OR(Q4="",Q4=0,O4=""),"",O4/Q4) | AC4: 1832 Middleton St., Georgetown, SC. Judgment $ not pulled yet (needs the PC run). Deficiency waived — final on the day.
A5: Georgetown | B5: 46273 | D5: 2025-CP-22-01043 | E5: cancelled | F5: 147 Rubin Av., Georgetown, SC | G5: 02-0203-039-00-00 | H5: Nationstar Mortgage | I5: David J. Smith | J5: waived | N5: =IF(OR(B5="",L5=""),"",MAX(0,B5-L5)) | O5: =IF(K5="","",K5+IF(OR(M5="",N5=""),0,M5*N5)) | R5: =IF(OR(Q5="",Q5=0,O5=""),"",O5/Q5) | AC5: 147 Rubin Av., Georgetown, SC. Judgment $ not pulled yet (needs the PC run). Deficiency waived — final on the day. STATUS: CANCELLED.
A6: Georgetown | B6: 46273 | D6: 2025-CP-22-00093 | E6: scheduled | F6: 73 Magill Lane, Georgetown, SC | G6: 01-0120-047-00-00 | H6: REV Federal Cred. Union | I6: Ralph Hoffman | J6: demanded | N6: =IF(OR(B6="",L6=""),"",MAX(0,B6-L6)) | O6: =IF(K6="","",K6+IF(OR(M6="",N6=""),0,M6*N6)) | R6: =IF(OR(Q6="",Q6=0,O6=""),"",O6/Q6) | AC6: 73 Magill Lane, Georgetown, SC. Judgment $ not pulled yet (needs the PC run). DEFICIENCY DEMANDED — open 30 days.
A7: Georgetown | B7: 46273 | D7: 2025-CP-22-00127 | E7: scheduled | F7: 5457 Huntington Marsh Rd., Murrells Inlet, SC | G7: 04-0101-005-00-00 | H7: Selene Finance | I7: John H. Oakes | J7: waived | N7: =IF(OR(B7="",L7=""),"",MAX(0,B7-L7)) | O7: =IF(K7="","",K7+IF(OR(M7="",N7=""),0,M7*N7)) | R7: =IF(OR(Q7="",Q7=0,O7=""),"",O7/Q7) | AC7: 5457 Huntington Marsh Rd., Murrells Inlet, SC. Judgment $ not pulled yet (needs the PC run). Deficiency waived — final on the day.
A8: Georgetown | B8: 46273 | D8: 2025-CP-22-00906 | E8: scheduled | F8: 23 Orchard Ave., Murrells Inlet, SC | G8: 41-0118-008-01-24 | H8: Citibank, N.A. | I8: Kim Brackett | J8: waived | N8: =IF(OR(B8="",L8=""),"",MAX(0,B8-L8)) | O8: =IF(K8="","",K8+IF(OR(M8="",N8=""),0,M8*N8)) | R8: =IF(OR(Q8="",Q8=0,O8=""),"",O8/Q8) | AC8: 23 Orchard Ave., Murrells Inlet, SC. Judgment $ not pulled yet (needs the PC run). Deficiency waived — final on the day.
A9: Greenville | B9: 46273 | C9: 1 | D9: 2016-CP-23-06737 | E9: withdrawn | F9: 128 Wild Dogwood Way Greenville, SC 29605 | H9: American Capital Group, LLC | I9: Louise A. Schiminger | J9: demanded | N9: =IF(OR(B9="",L9=""),"",MAX(0,B9-L9)) | O9: =IF(K9="","",K9+IF(OR(M9="",N9=""),0,M9*N9)) | R9: =IF(OR(Q9="",Q9=0,O9=""),"",O9/Q9) | Z9: open | AC9: 128 Wild Dogwood Way Greenville, SC 29605. Judgment $ not pulled yet (needs the PC run). DEFICIENCY DEMANDED — open 30 days. STATUS: WITHDRAWN.
A10: Greenville | B10: 46273 | C10: 2 | D10: 2024-CP-23-03628 | E10: scheduled | F10: 9-A Stadium Drive Greenville, SC 29609 | H10: HSBC Bank USA, N.A., as Trustee for ACE Securities Corp. Home Equity Loan Trust, Series 2007-HE2 | I10: Heirs-at-law or devisees of Edgar B. Walker, deceased, et al | J10: waived | K10: 94593 | N10: =IF(OR(B10="",L10=""),"",MAX(0,B10-L10)) | O10: =IF(K10="","",K10+IF(OR(M10="",N10=""),0,M10*N10)) | Q10: 218570 | R10: =IF(OR(Q10="",Q10=0,O10=""),"",O10/Q10) | S10: 0.520 | T10: 1100 (Single Family) | W10: Walker Lonietta Y | X10: 06/30/2006 $98,000 | Y10: open | Z10: open | AB10: open | AC10: 9-A Stadium Drive Greenville, SC 29609 — 1100 (Single Family) — 0.520 ac. Record owner Walker Lonietta Y. Last transfer 06/30/2006 for $98,000. County FMV $218,570.00. Judgment $94,593.00. Debt is 43% of FMV — real equity, expect third-party bidding. Deficiency waived — final on the day.
A11: Greenville | B11: 46273 | C11: 3 | D11: 2024-CP-23-07423 | E11: scheduled | F11: 304 Weddington Lane Simpsonville, SC 29681 | H11: New Silver Lending, LLC | I11: Key-Line Capital Investment Group, LLC | J11: demanded | K11: 331126 | N11: =IF(OR(B11="",L11=""),"",MAX(0,B11-L11)) | O11: =IF(K11="","",K11+IF(OR(M11="",N11=""),0,M11*N11)) | Q11: 95000 | R11: =IF(OR(Q11="",Q11=0,O11=""),"",O11/Q11) | S11: 0.150 | T11: 1180 (Residential Vacant) | W11: Key-Line Capital Investment Gr | X11: 01/23/2024 $5 | Y11: open | Z11: open | AB11: open | AC11: 304 Weddington Lane Simpsonville, SC 29681 — 1180 (Residential Vacant) — 0.150 ac (Linden Park). Record owner Key-Line Capital Investment Gr. Last transfer 01/23/2024 for $5. County FMV $95,000.00. Judgment $331,126.00. Debt exceeds FMV (349%) — plaintiff will likely take it back. DEFICIENCY DEMANDED — open 30 days.
A12: Greenville | B12: 46273 | C12: 4 | D12: 2025-CP-23-03722 | E12: scheduled | F12: 608 Rhett Street Greenville, SC 29601 | H12: Kiavi Funding, Inc. | I12: VSWC LLC | J12: demanded | K12: 482293 | N12: =IF(OR(B12="",L12=""),"",MAX(0,B12-L12)) | O12: =IF(K12="","",K12+IF(OR(M12="",N12=""),0,M12*N12)) | Q12: 392670 | R12: =IF(OR(Q12="",Q12=0,O12=""),"",O12/Q12) | S12: 0.100 | T12: 1100 (Single Family) | W12: Vswc Llc | X12: 11/13/2023 $400,000 | Y12: open | Z12: open | AB12: open | AC12: 608 Rhett Street Greenville, SC 29601 — 1100 (Single Family) — 0.100 ac. Record owner Vswc Llc. Last transfer 11/13/2023 for $400,000. County FMV $392,670.00. Judgment $482,293.00. Debt exceeds FMV (123%) — plaintiff will likely take it back. DEFICIENCY DEMANDED — open 30 days.
A13: Greenville | B13: 46273 | C13: 5 | D13: 2025-CP-23-05048 | E13: scheduled | F13: 4 Point Hope Court Greenville, SC 29605 | H13: South Carolina State Housing Finance and Development Authority | I13: Sharon Diane Culpepper-Booker | J13: waived | K13: 179057 | N13: =IF(OR(B13="",L13=""),"",MAX(0,B13-L13)) | O13: =IF(K13="","",K13+IF(OR(M13="",N13=""),0,M13*N13)) | Q13: 235180 | R13: =IF(OR(Q13="",Q13=0,O13=""),"",O13/Q13) | S13: 0 | T13: 1100 (Single Family) | W13: Culpepper-Booker Sharon Diane | X13: 09/29/2020 $179,000 | Y13: open | Z13: open | AB13: open | AC13: 4 Point Hope Court Greenville, SC 29605 — 1100 (Single Family) (Oak Knoll). Record owner Culpepper-Booker Sharon Diane. Last transfer 09/29/2020 for $179,000. County FMV $235,180.00. Judgment $179,057.00. Debt is 76% of FMV — thin margin. Deficiency waived — final on the day.
A14: Greenville | B14: 46273 | C14: 6 | D14: 2025-CP-23-06065 | E14: withdrawn | F14: 110 Water Reach Lane Simpsonville, SC 29681 | H14: SELENE FINANCE LP | I14: John Clement Shaugnessy | J14: waived | N14: =IF(OR(B14="",L14=""),"",MAX(0,B14-L14)) | O14: =IF(K14="","",K14+IF(OR(M14="",N14=""),0,M14*N14)) | R14: =IF(OR(Q14="",Q14=0,O14=""),"",O14/Q14) | Z14: open | AC14: 110 Water Reach Lane Simpsonville, SC 29681. Judgment $ not pulled yet (needs the PC run). Deficiency waived — final on the day. STATUS: WITHDRAWN.
A15: Greenville | B15: 46273 | C15: 7 | D15: 2025-CP-23-06198 | E15: withdrawn | F15: 603 Stallings Rd Taylors, SC 29687 | H15: Planet Home Lending, LLC | I15: Crystal Lynn Patterson | J15: waived | N15: =IF(OR(B15="",L15=""),"",MAX(0,B15-L15)) | O15: =IF(K15="","",K15+IF(OR(M15="",N15=""),0,M15*N15)) | R15: =IF(OR(Q15="",Q15=0,O15=""),"",O15/Q15) | Z15: open | AC15: 603 Stallings Rd Taylors, SC 29687. Judgment $ not pulled yet (needs the PC run). Deficiency waived — final on the day. STATUS: WITHDRAWN.
A16: Greenville | B16: 46273 | C16: 8 | D16: 2025-CP-23-06584 | E16: scheduled | F16: 39B W Golden Strip Drive Mauldin, SC 29662 | H16: South Carolina State Housing Finance and Development Authority | I16: Dominique Smith | J16: waived | K16: 68468.05 | N16: =IF(OR(B16="",L16=""),"",MAX(0,B16-L16)) | O16: =IF(K16="","",K16+IF(OR(M16="",N16=""),0,M16*N16)) | Q16: 244440 | R16: =IF(OR(Q16="",Q16=0,O16=""),"",O16/Q16) | S16: 0.340 | T16: 1100 (Single Family) | W16: Ladson Alice D | X16: 05/20/2014 $132,500 | Y16: open | Z16: open | AB16: open | AC16: 39B W Golden Strip Drive Mauldin, SC 29662 — 1100 (Single Family) — 0.340 ac. Record owner Ladson Alice D (card is for 39 W GOLDEN STRIP DR — unit letter not on file, verify). Last transfer 05/20/2014 for $132,500. County FMV $244,440.00. Judgment $68,468.05. Debt is 28% of FMV — real equity, expect third-party bidding. Deficiency waived — final on the day.
A17: Greenville | B17: 46273 | C17: 9 | D17: 2025-CP-23-06604 | E17: scheduled | F17: 15 Fennec Drive Fountain Inn, SC 29644 | H17: South Carolina State Housing Finance and Development Authority | I17: Brandon Andre Roane | J17: demanded | K17: 279737 | N17: =IF(OR(B17="",L17=""),"",MAX(0,B17-L17)) | O17: =IF(K17="","",K17+IF(OR(M17="",N17=""),0,M17*N17)) | Q17: 289220 | R17: =IF(OR(Q17="",Q17=0,O17=""),"",O17/Q17) | S17: 0 | T17: 1100 (Single Family) | W17: Roane Brandon Andre | X17: 05/11/2023 $262,999 | Y17: open | Z17: open | AB17: open | AC17: 15 Fennec Drive Fountain Inn, SC 29644 — 1100 (Single Family) (Fox Tail Cottages). Record owner Roane Brandon Andre. Last transfer 05/11/2023 for $262,999. County FMV $289,220.00. Judgment $279,737.00. Debt is 97% of FMV — thin margin. DEFICIENCY DEMANDED — open 30 days.
A18: Greenville | B18: 46273 | C18: 10 | D18: 2025-CP-23-06612 | E18: scheduled | F18: 104 Pine Needle Road Piedmont, SC 29673 | H18: South Carolina State Housing Finance and Development Authority | I18: Ashley Rhodes | J18: waived | K18: 254440 | N18: =IF(OR(B18="",L18=""),"",MAX(0,B18-L18)) | O18: =IF(K18="","",K18+IF(OR(M18="",N18=""),0,M18*N18)) | Q18: 212830 | R18: =IF(OR(Q18="",Q18=0,O18=""),"",O18/Q18) | S18: 0 | T18: 1100 (Single Family) | W18: Rhodes Ashley | X18: 01/17/2024 $222,500 | Y18: open | Z18: open | AB18: open | AC18: 104 Pine Needle Road Piedmont, SC 29673 — 1100 (Single Family) (Pine Shadows). Record owner Rhodes Ashley. Last transfer 01/17/2024 for $222,500. County FMV $212,830.00. Judgment $254,440.00. Debt exceeds FMV (120%) — plaintiff will likely take it back. Deficiency waived — final on the day.
A19: Greenville | B19: 46273 | C19: 11 | D19: 2025-CP-23-07189 | E19: scheduled | F19: 402 Sienna Drive Greenville, SC 29609 | H19: U.S. Bank Trust National Association, as trustee for Legacy Mortgage Asset Trust 2021-GS4 | I19: Terry Tolbert | J19: waived | K19: 906485 | N19: =IF(OR(B19="",L19=""),"",MAX(0,B19-L19)) | O19: =IF(K19="","",K19+IF(OR(M19="",N19=""),0,M19*N19)) | R19: =IF(OR(Q19="",Q19=0,O19=""),"",O19/Q19) | Y19: open | Z19: open | AC19: 402 Sienna Drive Greenville, SC 29609. Judgment $906,485.00. Deficiency waived — final on the day.
A20: Greenville | B20: 46273 | C20: 12 | D20: 2025-CP-23-07612 | E20: scheduled | F20: 3 Black Oak Court Simpsonville, SC 29680 | H20: South Carolina State Housing Finance and Development Authority | I20: Maria Harley | J20: waived | K20: 269097 | N20: =IF(OR(B20="",L20=""),"",MAX(0,B20-L20)) | O20: =IF(K20="","",K20+IF(OR(M20="",N20=""),0,M20*N20)) | Q20: 278430 | R20: =IF(OR(Q20="",Q20=0,O20=""),"",O20/Q20) | S20: 0 | T20: 1100 (Single Family) | W20: Harley Maria | X20: 11/15/2023 $244,900 | Y20: open | Z20: open | AB20: open | AC20: 3 Black Oak Court Simpsonville, SC 29680 — 1100 (Single Family) (Standing Springs Estate). Record owner Harley Maria. Last transfer 11/15/2023 for $244,900. County FMV $278,430.00. Judgment $269,097.00. Debt is 97% of FMV — thin margin. Deficiency waived — final on the day.
A21: Greenville | B21: 46273 | C21: 13 | D21: 2025-CP-23-07667 | E21: withdrawn | F21: 406 Sandusky Lane Simpsonville, SC 29680 | H21: River Shoals Homeowners Association Inc | I21: Nancy Abad | J21: waived | N21: =IF(OR(B21="",L21=""),"",MAX(0,B21-L21)) | O21: =IF(K21="","",K21+IF(OR(M21="",N21=""),0,M21*N21)) | R21: =IF(OR(Q21="",Q21=0,O21=""),"",O21/Q21) | Z21: open | AC21: 406 Sandusky Lane Simpsonville, SC 29680. Judgment $ not pulled yet (needs the PC run). Deficiency waived — final on the day. STATUS: WITHDRAWN.
A22: Greenville | B22: 46273 | C22: 14 | D22: 2025-CP-23-08344 | E22: withdrawn | F22: 1904 Lake Cunningham Road Greer, SC 29651 | H22: New American Funding LLC f/k/a Broker Solutions, Inc. | I22: Michael Greene | J22: waived | N22: =IF(OR(B22="",L22=""),"",MAX(0,B22-L22)) | O22: =IF(K22="","",K22+IF(OR(M22="",N22=""),0,M22*N22)) | Q22: 410930 | R22: =IF(OR(Q22="",Q22=0,O22=""),"",O22/Q22) | S22: 0 | T22: 1170 (MH w/ land) | W22: Morales-Greene Emilia | X22: 06/27/2025 | Z22: open | AB22: open | AC22: 1904 Lake Cunningham Road Greer, SC 29651 — 1170 (MH w/ land) (Cunningham Downs). Record owner Morales-Greene Emilia. Last transfer 06/27/2025. County FMV $410,930.00. Judgment $ not pulled yet (needs the PC run). Deficiency waived — final on the day. STATUS: WITHDRAWN.
A23: Greenville | B23: 46273 | C23: 15 | D23: 2025-CP-23-08409 | E23: withdrawn | F23: 116 Ridgewater Court Fountain Inn, SC 29644 | H23: US Bank Trust National Association, as owner trustee for VRMTG Asset Trust | I23: Kathleen DeFrancesco | J23: waived | N23: =IF(OR(B23="",L23=""),"",MAX(0,B23-L23)) | O23: =IF(K23="","",K23+IF(OR(M23="",N23=""),0,M23*N23)) | R23: =IF(OR(Q23="",Q23=0,O23=""),"",O23/Q23) | Z23: open | AC23: 116 Ridgewater Court Fountain Inn, SC 29644. Judgment $ not pulled yet (needs the PC run). Deficiency waived — final on the day. STATUS: WITHDRAWN.
A24: Greenville | B24: 46273 | C24: 16 | D24: 2026-CP-23-00155 | E24: scheduled | F24: 1406 Winding Way Taylors, SC 29687 | H24: Rocket Mortgage, LLC f/k/a Quicken Loans, LLC | I24: Philip W. Dixon | J24: demanded | K24: 107886 | N24: =IF(OR(B24="",L24=""),"",MAX(0,B24-L24)) | O24: =IF(K24="","",K24+IF(OR(M24="",N24=""),0,M24*N24)) | Q24: 254770 | R24: =IF(OR(Q24="",Q24=0,O24=""),"",O24/Q24) | S24: 0 | T24: 1100 (Single Family) | W24: Dixon Sue Ann | X24: 12/01/2009 $10 | Y24: open | Z24: open | AB24: open | AC24: 1406 Winding Way Taylors, SC 29687 — 1100 (Single Family) (Peppertree). Record owner Dixon Sue Ann. Last transfer 12/01/2009 for $10. County FMV $254,770.00. Judgment $107,886.00. Debt is 42% of FMV — real equity, expect third-party bidding. DEFICIENCY DEMANDED — open 30 days.
A25: Greenville | B25: 46273 | C25: 17 | D25: 2026-CP-23-00195 | E25: withdrawn | F25: 19 and 21 Whiller Drive Greenville, SC 29608 | H25: Moneyline Ventures, LLC | I25: A.S.K. Enterprises & Funding, LLC | J25: waived | N25: =IF(OR(B25="",L25=""),"",MAX(0,B25-L25)) | O25: =IF(K25="","",K25+IF(OR(M25="",N25=""),0,M25*N25)) | R25: =IF(OR(Q25="",Q25=0,O25=""),"",O25/Q25) | Z25: open | AC25: 19 and 21 Whiller Drive Greenville, SC 29608. Judgment $ not pulled yet (needs the PC run). Deficiency waived — final on the day. STATUS: WITHDRAWN.
A26: Greenville | B26: 46273 | C26: 18 | D26: 2026-CP-23-00512 | E26: scheduled | F26: 104 Oak Forest Drive Greer, SC 29650 | H26: Carrington Mortgage Services, LLC | I26: Chad Thompson | J26: waived | K26: 408231 | N26: =IF(OR(B26="",L26=""),"",MAX(0,B26-L26)) | O26: =IF(K26="","",K26+IF(OR(M26="",N26=""),0,M26*N26)) | Q26: 522800 | R26: =IF(OR(Q26="",Q26=0,O26=""),"",O26/Q26) | S26: 0 | T26: 1100 (Single Family) | W26: Thompson Chad | X26: 04/11/2022 $389,900 | Y26: open | Z26: open | AB26: open | AC26: 104 Oak Forest Drive Greer, SC 29650 — 1100 (Single Family). Record owner Thompson Chad. Last transfer 04/11/2022 for $389,900. County FMV $522,800.00. Judgment $408,231.00. Debt is 78% of FMV — thin margin. Deficiency waived — final on the day.
A27: Greenville | B27: 46273 | C27: 19 | D27: 2026-CP-23-00555 | E27: withdrawn | F27: 67 Wallace Street Greenville, SC 29605 | H27: Greenville County Redevelopment Authority | I27: Sylvia G. Hammett | J27: waived | N27: =IF(OR(B27="",L27=""),"",MAX(0,B27-L27)) | O27: =IF(K27="","",K27+IF(OR(M27="",N27=""),0,M27*N27)) | R27: =IF(OR(Q27="",Q27=0,O27=""),"",O27/Q27) | Z27: open | AC27: 67 Wallace Street Greenville, SC 29605. Judgment $ not pulled yet (needs the PC run). Deficiency waived — final on the day. STATUS: WITHDRAWN.
A28: Greenville | B28: 46273 | C28: 20 | D28: 2026-CP-23-00730 | E28: scheduled | F28: 100 N. Markley St. Greenville, SC 29601 | H28: The Fidelity Bank | I28: Greenville HKW, LLC | J28: waived | K28: 4572030.1 | N28: =IF(OR(B28="",L28=""),"",MAX(0,B28-L28)) | O28: =IF(K28="","",K28+IF(OR(M28="",N28=""),0,M28*N28)) | Q28: 2973000 | R28: =IF(OR(Q28="",Q28=0,O28=""),"",O28/Q28) | S28: 0.910 | T28: 6800 (Commercial Vacant ) | W28: Greenville Hkw Llc | X28: 12/16/2019 | Y28: open | Z28: open | AB28: open | AC28: 100 N. Markley St. Greenville, SC 29601 — 6800 (Commercial Vacant ) — 0.910 ac. Record owner Greenville Hkw Llc. Last transfer 12/16/2019. County FMV $2,973,000.00. Judgment $4,572,030.10. Debt exceeds FMV (154%) — plaintiff will likely take it back. Deficiency waived — final on the day.
A29: Greenville | B29: 46273 | C29: 21 | D29: 2026-CP-23-01255 | E29: withdrawn | F29: 23 Chinaberry Lane Simpsonville, SC 29680 | H29: Truist Bank | I29: Doris B. Pressley | J29: waived | N29: =IF(OR(B29="",L29=""),"",MAX(0,B29-L29)) | O29: =IF(K29="","",K29+IF(OR(M29="",N29=""),0,M29*N29)) | R29: =IF(OR(Q29="",Q29=0,O29=""),"",O29/Q29) | Z29: open | AC29: 23 Chinaberry Lane Simpsonville, SC 29680. Judgment $ not pulled yet (needs the PC run). Deficiency waived — final on the day. STATUS: WITHDRAWN.
A30: Greenville | B30: 46273 | C30: 22 | D30: 2026-CP-23-01348 | E30: withdrawn | F30: 302 West Road Travelers Rest, SC 29690 | H30: Rocket Mortgage, LLC f/k/a Quicken Loans, LLC | I30: Wanda Brown | J30: waived | N30: =IF(OR(B30="",L30=""),"",MAX(0,B30-L30)) | O30: =IF(K30="","",K30+IF(OR(M30="",N30=""),0,M30*N30)) | R30: =IF(OR(Q30="",Q30=0,O30=""),"",O30/Q30) | Z30: open | AC30: 302 West Road Travelers Rest, SC 29690. Judgment $ not pulled yet (needs the PC run). Deficiency waived — final on the day. STATUS: WITHDRAWN.
A31: Greenville | B31: 46273 | C31: 23 | D31: 2026-CP-23-01483 | E31: scheduled | F31: 304 Glenlea Ln Greenville, SC 29617 | H31: Finance of America Reverse LLC | I31: Robert Luther Ellis, Jr as Personal Representative for the Estate of Beverly Staton | J31: waived | K31: 153841.1 | N31: =IF(OR(B31="",L31=""),"",MAX(0,B31-L31)) | O31: =IF(K31="","",K31+IF(OR(M31="",N31=""),0,M31*N31)) | Q31: 224920 | R31: =IF(OR(Q31="",Q31=0,O31=""),"",O31/Q31) | S31: 0.120 | T31: 1100 (Single Family) | W31: Staton Beverly | X31: 11/15/2004 $105,000 | Y31: open | Z31: open | AB31: open | AC31: 304 Glenlea Ln Greenville, SC 29617 — 1100 (Single Family) — 0.120 ac (The Village At Glenlea). Record owner Staton Beverly. Last transfer 11/15/2004 for $105,000. County FMV $224,920.00. Judgment $153,841.10. Debt is 68% of FMV — real equity, expect third-party bidding. Deficiency waived — final on the day.
A32: Greenville | B32: 46273 | C32: 24 | D32: 2026-CP-23-02327 | E32: scheduled | F32: 71 Dorsey Avenue Greenville, SC 29611 | H32: Wilmington Savings Fund Society, FSB, as Owner Trustee for the FLIC Residential Mortgage Loan Trust 1 | I32: VSWC LLC | J32: waived | K32: 246879.23 | N32: =IF(OR(B32="",L32=""),"",MAX(0,B32-L32)) | O32: =IF(K32="","",K32+IF(OR(M32="",N32=""),0,M32*N32)) | Q32: 246770 | R32: =IF(OR(Q32="",Q32=0,O32=""),"",O32/Q32) | S32: 0.210 | T32: 1100 (Single Family) | W32: Vswc Llc | X32: 10/05/2021 $100,000 | Y32: open | Z32: open | AB32: open | AC32: 71 Dorsey Avenue Greenville, SC 29611 — 1100 (Single Family) — 0.210 ac (Abney Mills). Record owner Vswc Llc. Last transfer 10/05/2021 for $100,000. County FMV $246,770.00. Judgment $246,879.23. Debt exceeds FMV (100%) — plaintiff will likely take it back. Deficiency waived — final on the day.
A33: Greenville | B33: 46273 | C33: 25 | D33: 2026-CP-23-02343 | E33: scheduled | F33: 37 Ross Street Greenville, SC 29611 | H33: Wilmington Savings Fund Society, FSB, as Trustee of NMLT 2021-INV1 Trust | I33: VSWC LLC | J33: waived | K33: 159379.2 | N33: =IF(OR(B33="",L33=""),"",MAX(0,B33-L33)) | O33: =IF(K33="","",K33+IF(OR(M33="",N33=""),0,M33*N33)) | Q33: 183180 | R33: =IF(OR(Q33="",Q33=0,O33=""),"",O33/Q33) | S33: 0 | T33: 1100 (Single Family) | W33: Vswc Llc | X33: 05/21/2020 $10 | Y33: open | Z33: open | AB33: open | AC33: 37 Ross Street Greenville, SC 29611 — 1100 (Single Family). Record owner Vswc Llc. Last transfer 05/21/2020 for $10. County FMV $183,180.00. Judgment $159,379.20. Debt is 87% of FMV — thin margin. Deficiency waived — final on the day.
A34: Greenville | B34: 46273 | C34: 26 | D34: 2026-CP-23-02408 | E34: scheduled | F34: 11 Charing Cross Road Taylors, SC 29687 | H34: Wilmington Savings Fund Society, FSB, as trustee for Ibis Holdings A Trust | I34: GRM Properties | J34: demanded | K34: 219174.3 | N34: =IF(OR(B34="",L34=""),"",MAX(0,B34-L34)) | O34: =IF(K34="","",K34+IF(OR(M34="",N34=""),0,M34*N34)) | Q34: 267670 | R34: =IF(OR(Q34="",Q34=0,O34=""),"",O34/Q34) | S34: 0 | T34: 1100 (Single Family) | W34: Grm Properties Of South Caroli | X34: 08/12/2022 $235,000 | Y34: open | Z34: open | AB34: open | AC34: 11 Charing Cross Road Taylors, SC 29687 — 1100 (Single Family) (Brookwood Forest). Record owner Grm Properties Of South Caroli. Last transfer 08/12/2022 for $235,000. County FMV $267,670.00. Judgment $219,174.30. Debt is 82% of FMV — thin margin. DEFICIENCY DEMANDED — open 30 days.
A35: Greenville | B35: 46273 | C35: 27 | D35: 2026-CP-23-02884 | E35: scheduled | F35: 2501 Poinsett Highway Greenville, SC 29609 | H35: ALFIE Investors LLC | I35: 2501 Poinsette LLC | J35: demanded | K35: 301030.64 | N35: =IF(OR(B35="",L35=""),"",MAX(0,B35-L35)) | O35: =IF(K35="","",K35+IF(OR(M35="",N35=""),0,M35*N35)) | Q35: 306870 | R35: =IF(OR(Q35="",Q35=0,O35=""),"",O35/Q35) | S35: 0 | T35: 1100 (Single Family) | W35: 2501 Poinsette Llc | X35: 05/02/2022 $130,000 | Y35: open | Z35: open | AB35: open | AC35: 2501 Poinsett Highway Greenville, SC 29609 — 1100 (Single Family). Record owner 2501 Poinsette Llc. Last transfer 05/02/2022 for $130,000. County FMV $306,870.00. Judgment $301,030.64. Debt is 98% of FMV — thin margin. DEFICIENCY DEMANDED — open 30 days.
A36: Greenville | B36: 46273 | C36: 28 | D36: 2026-CP-23-03000 | E36: scheduled | F36: 202 Port Road Greenville, SC 29617 | H36: UMB Bank, National Association, as owner trustee for Verus Securitization Trust 2024-6 | I36: Green Ant LLC | J36: waived | K36: 221056.42 | N36: =IF(OR(B36="",L36=""),"",MAX(0,B36-L36)) | O36: =IF(K36="","",K36+IF(OR(M36="",N36=""),0,M36*N36)) | Q36: 249890 | R36: =IF(OR(Q36="",Q36=0,O36=""),"",O36/Q36) | S36: 0.590 | T36: 1100 (Single Family) | W36: Green Ant Llc | X36: 05/16/2023 $249,900 | Y36: open | Z36: open | AB36: open | AC36: 202 Port Road Greenville, SC 29617 — 1100 (Single Family) — 0.590 ac (River Valley). Record owner Green Ant Llc. Last transfer 05/16/2023 for $249,900. County FMV $249,890.00. Judgment $221,056.42. Debt is 88% of FMV — thin margin. Deficiency waived — final on the day.
A37: Greenville | B37: 46273 | C37: 29 | D37: 2026-CP-23-03232 | E37: withdrawn | F37: 608 Kingsmoor Drive Simpsonville, SC 29681 | H37: Mortgage Solutions of Colorado, LLC d/b/a Mortgage Solutions Financial | I37: Josh Massengill | J37: waived | N37: =IF(OR(B37="",L37=""),"",MAX(0,B37-L37)) | O37: =IF(K37="","",K37+IF(OR(M37="",N37=""),0,M37*N37)) | R37: =IF(OR(Q37="",Q37=0,O37=""),"",O37/Q37) | Z37: open | AC37: 608 Kingsmoor Drive Simpsonville, SC 29681. Judgment $ not pulled yet (needs the PC run). Deficiency waived — final on the day. STATUS: WITHDRAWN.
A38: Horry | B38: 46273 | D38: 2026-CP-26-02004 | E38: scheduled | F38: 1207 S Ocean Blvd, Unit 50801, Myrtle Beach, SC 29577 | G38: 1811302158 | J38: demanded | K38: 77686.29 | N38: =IF(OR(B38="",L38=""),"",MAX(0,B38-L38)) | O38: =IF(K38="","",K38+IF(OR(M38="",N38=""),0,M38*N38)) | R38: =IF(OR(Q38="",Q38=0,O38=""),"",O38/Q38) | Y38: open | AC38: 1207 S Ocean Blvd, Unit 50801, Myrtle Beach, SC 29577. Judgment $77,686.29. DEFICIENCY DEMANDED — open 30 days.
A39: Horry | B39: 46273 | D39: 2026-CP-26-02004 | E39: scheduled | F39: 1207 S Ocean Blvd, Unit 50901, Myrtle Beach, SC 29577 | G39: 1811302171 | J39: demanded | K39: 77686.29 | N39: =IF(OR(B39="",L39=""),"",MAX(0,B39-L39)) | O39: =IF(K39="","",K39+IF(OR(M39="",N39=""),0,M39*N39)) | R39: =IF(OR(Q39="",Q39=0,O39=""),"",O39/Q39) | Y39: open | AC39: 1207 S Ocean Blvd, Unit 50901, Myrtle Beach, SC 29577. Judgment $77,686.29. DEFICIENCY DEMANDED — open 30 days.
A40: Horry | B40: 46273 | D40: 2026-CP-26-02004 | E40: scheduled | F40: 1207 S Ocean Blvd, Unit 50902, Myrtle Beach, SC 29577 | G40: 1811302172 | J40: demanded | K40: 77686.29 | N40: =IF(OR(B40="",L40=""),"",MAX(0,B40-L40)) | O40: =IF(K40="","",K40+IF(OR(M40="",N40=""),0,M40*N40)) | R40: =IF(OR(Q40="",Q40=0,O40=""),"",O40/Q40) | Y40: open | AC40: 1207 S Ocean Blvd, Unit 50902, Myrtle Beach, SC 29577. Judgment $77,686.29. DEFICIENCY DEMANDED — open 30 days.
A41: Horry | B41: 46273 | D41: 2026-CP-26-02004 | E41: scheduled | F41: 1207 S Ocean Blvd, Unit 51002, Myrtle Beach, SC 29577 | G41: 1811302185 | J41: demanded | K41: 77871.12 | N41: =IF(OR(B41="",L41=""),"",MAX(0,B41-L41)) | O41: =IF(K41="","",K41+IF(OR(M41="",N41=""),0,M41*N41)) | R41: =IF(OR(Q41="",Q41=0,O41=""),"",O41/Q41) | Y41: open | AC41: 1207 S Ocean Blvd, Unit 51002, Myrtle Beach, SC 29577. Judgment $77,871.12. DEFICIENCY DEMANDED — open 30 days.
A42: Horry | B42: 46273 | D42: 2026-CP-26-00352 | E42: scheduled | F42: 4405 Hwy 378, Conway, SC 29527 | G42: 1350002025 | J42: waived | K42: 321970.72 | N42: =IF(OR(B42="",L42=""),"",MAX(0,B42-L42)) | O42: =IF(K42="","",K42+IF(OR(M42="",N42=""),0,M42*N42)) | R42: =IF(OR(Q42="",Q42=0,O42=""),"",O42/Q42) | Y42: open | AC42: 4405 Hwy 378, Conway, SC 29527. Judgment $321,970.72. Deficiency waived — final on the day.
A43: Horry | B43: 46273 | D43: 2026-CP-26-00505 | E43: scheduled | F43: 3004 Sawyer Street, Conway, SC 29527 | G43: 1361206049 | J43: demanded | K43: 110851.62 | N43: =IF(OR(B43="",L43=""),"",MAX(0,B43-L43)) | O43: =IF(K43="","",K43+IF(OR(M43="",N43=""),0,M43*N43)) | R43: =IF(OR(Q43="",Q43=0,O43=""),"",O43/Q43) | Y43: open | AC43: 3004 Sawyer Street, Conway, SC 29527. Judgment $110,851.62. DEFICIENCY DEMANDED — open 30 days.
A44: Horry | B44: 46273 | D44: 2025-CP-26-08343 | E44: scheduled | F44: 4149 Hibiscus Dr., Apt. 204, Little River, SC 29566 | G44: 1312802206 | J44: waived | K44: 69762.07 | N44: =IF(OR(B44="",L44=""),"",MAX(0,B44-L44)) | O44: =IF(K44="","",K44+IF(OR(M44="",N44=""),0,M44*N44)) | R44: =IF(OR(Q44="",Q44=0,O44=""),"",O44/Q44) | Y44: open | AC44: 4149 Hibiscus Dr., Apt. 204, Little River, SC 29566. Judgment $69,762.07. Deficiency waived — final on the day.
A45: Horry | B45: 46273 | D45: 2026-CP-26-01100 | E45: scheduled | F45: 1501 S Ocean Blvd., Unit 234, Myrtle Beach, SC 29577 | G45: 1870106170 | J45: waived | K45: 68321.86 | N45: =IF(OR(B45="",L45=""),"",MAX(0,B45-L45)) | O45: =IF(K45="","",K45+IF(OR(M45="",N45=""),0,M45*N45)) | R45: =IF(OR(Q45="",Q45=0,O45=""),"",O45/Q45) | Y45: open | AC45: 1501 S Ocean Blvd., Unit 234, Myrtle Beach, SC 29577. Judgment $68,321.86. Deficiency waived — final on the day.
A46: Horry | B46: 46273 | D46: 2026-CP-26-00092 | E46: scheduled | F46: 1009 World Tour Blvd., Unit 101A, Myrtle Beach, SC 29579 | G46: 1723701365 | J46: demanded | K46: 195340.71 | N46: =IF(OR(B46="",L46=""),"",MAX(0,B46-L46)) | O46: =IF(K46="","",K46+IF(OR(M46="",N46=""),0,M46*N46)) | R46: =IF(OR(Q46="",Q46=0,O46=""),"",O46/Q46) | Y46: open | AC46: 1009 World Tour Blvd., Unit 101A, Myrtle Beach, SC 29579. Judgment $195,340.71. DEFICIENCY DEMANDED — open 30 days.
A47: Horry | B47: 46273 | D47: 2026-CP-26-01639 | E47: scheduled | F47: 1501 S Ocean Blvd, Unit 1003, Myrtle Beach, SC 29577 | G47: 1870106637 | J47: waived | K47: 102682.37 | N47: =IF(OR(B47="",L47=""),"",MAX(0,B47-L47)) | O47: =IF(K47="","",K47+IF(OR(M47="",N47=""),0,M47*N47)) | R47: =IF(OR(Q47="",Q47=0,O47=""),"",O47/Q47) | Y47: open | AC47: 1501 S Ocean Blvd, Unit 1003, Myrtle Beach, SC 29577. Judgment $102,682.37. Deficiency waived — final on the day.
A48: Horry | B48: 46273 | D48: 2026-CP-26-00435 | E48: scheduled | F48: 4230 Pinehurst Circle, Unit K7, Little River, SC 29566 | G48: 1182101101 | J48: waived | K48: 11784.11 | N48: =IF(OR(B48="",L48=""),"",MAX(0,B48-L48)) | O48: =IF(K48="","",K48+IF(OR(M48="",N48=""),0,M48*N48)) | R48: =IF(OR(Q48="",Q48=0,O48=""),"",O48/Q48) | Y48: open | AC48: 4230 Pinehurst Circle, Unit K7, Little River, SC 29566. Judgment $11,784.11. Deficiency waived — final on the day.
A49: Horry | B49: 46273 | D49: 2026-CP-26-01969 | E49: scheduled | F49: 4834 Carnation Circle, Unit 105, Myrtle Beach, SC 29577 | G49: 1730401688 | J49: waived | K49: 10395.12 | N49: =IF(OR(B49="",L49=""),"",MAX(0,B49-L49)) | O49: =IF(K49="","",K49+IF(OR(M49="",N49=""),0,M49*N49)) | R49: =IF(OR(Q49="",Q49=0,O49=""),"",O49/Q49) | Y49: open | AC49: 4834 Carnation Circle, Unit 105, Myrtle Beach, SC 29577. Judgment $10,395.12. Deficiency waived — final on the day.
... A56: Horry | B56: 46273 | D56: 2025-CP-26-09288 | E56: scheduled | F56: 8329 Tartan Lane, Myrtle Beach, SC 29588 | G56: 1842601085 | J56: waived | K56: 329208.26 | N56: =IF(OR(B56="",L56=""),"",MAX(0,B56-L56)) | O56: =IF(K56="","",K56+IF(OR(M56="",N56=""),0,M56*N56)) | R56: =IF(OR(Q56="",Q56=0,O56=""),"",O56/Q56) | Y56: open | AC56: 8329 Tartan Lane, Myrtle Beach, SC 29588. Judgment $329,208.26. Deficiency waived — final on the day.
A57: Horry | B57: 46273 | D57: 2026-CP-26-00055 | E57: scheduled | F57: 2305 Copper Creek Loop, Longs, SC 29568 | J57: waived | K57: 404484.57 | N57: =IF(OR(B57="",L57=""),"",MAX(0,B57-L57)) | O57: =IF(K57="","",K57+IF(OR(M57="",N57=""),0,M57*N57)) | R57: =IF(OR(Q57="",Q57=0,O57=""),"",O57/Q57) | Y57: open | AC57: 2305 Copper Creek Loop, Longs, SC 29568. Judgment $404,484.57. Deficiency waived — final on the day.
A58: Horry | B58: 46273 | D58: 2026-CP-26-00133 | E58: scheduled | F58: 1108 Pochard Drive, Conway, SC 29526 | G58: 1514701074 | J58: waived | K58: 487011.42 | N58: =IF(OR(B58="",L58=""),"",MAX(0,B58-L58)) | O58: =IF(K58="","",K58+IF(OR(M58="",N58=""),0,M58*N58)) | R58: =IF(OR(Q58="",Q58=0,O58=""),"",O58/Q58) | Y58: open | AC58: 1108 Pochard Drive, Conway, SC 29526. Judgment $487,011.42. Deficiency waived — final on the day.
A59: Horry | B59: 46273 | D59: 2026-CP-26-00053 | E59: scheduled | F59: 665 Tupelo Lane, Unit 17 H, Longs, SC 29568 | G59: 1021801113 | J59: waived | K59: 204994.75 | N59: =IF(OR(B59="",L59=""),"",MAX(0,B59-L59)) | O59: =IF(K59="","",K59+IF(OR(M59="",N59=""),0,M59*N59)) | R59: =IF(OR(Q59="",Q59=0,O59=""),"",O59/Q59) | Y59: open | AC59: 665 Tupelo Lane, Unit 17 H, Longs, SC 29568. Judgment $204,994.75. Deficiency waived — final on the day.
A60: Horry | B60: 46273 | D60: 2026-CP-26-01835 | E60: scheduled | F60: 951 Plantation Drive A6, Little River, SC 29566 | J60: waived | K60: 273122.18 | N60: =IF(OR(B60="",L60=""),"",MAX(0,B60-L60)) | O60: =IF(K60="","",K60+IF(OR(M60="",N60=""),0,M60*N60)) | R60: =IF(OR(Q60="",Q60=0,O60=""),"",O60/Q60) | Y60: open | AC60: 951 Plantation Drive A6, Little River, SC 29566. Judgment $273,122.18. Deficiency waived — final on the day.
A61: Horry | B61: 46273 | D61: 2021-CP-26-00144 | E61: scheduled | F61: 3470 Hwy 917, Loris, SC 29569 | G61: 0370001160 | J61: waived | K61: 134479.81 | N61: =IF(OR(B61="",L61=""),"",MAX(0,B61-L61)) | O61: =IF(K61="","",K61+IF(OR(M61="",N61=""),0,M61*N61)) | R61: =IF(OR(Q61="",Q61=0,O61=""),"",O61/Q61) | Y61: open | AC61: 3470 Hwy 917, Loris, SC 29569. Judgment $134,479.81. Deficiency waived — final on the day.
A62: Horry | B62: 46273 | D62: 2021-CP-26-00252 | E62: scheduled | F62: 507 Sims Drive, Myrtle Beach, SC 29577 | G62: 1792211004 | J62: waived | K62: 98943.33 | N62: =IF(OR(B62="",L62=""),"",MAX(0,B62-L62)) | O62: =IF(K62="","",K62+IF(OR(M62="",N62=""),0,M62*N62)) | R62: =IF(OR(Q62="",Q62=0,O62=""),"",O62/Q62) | Y62: open | AC62: 507 Sims Drive, Myrtle Beach, SC 29577. Judgment $98,943.33. Deficiency waived — final on the day.
A63: Horry | B63: 46273 | D63: 2023-CP-26-04562 | E63: scheduled | F63: 308 Jasmine Drive, Conway, SC 29526 | G63: 1361701029 | J63: waived | K63: 232129.23 | N63: =IF(OR(B63="",L63=""),"",MAX(0,B63-L63)) | O63: =IF(K63="","",K63+IF(OR(M63="",N63=""),0,M63*N63)) | R63: =IF(OR(Q63="",Q63=0,O63=""),"",O63/Q63) | Y63: open | AC63: 308 Jasmine Drive, Conway, SC 29526. Judgment $232,129.23. Deficiency waived — final on the day.
A64: Horry | B64: 46273 | D64: 2023-CP-26-06121 | E64: scheduled | F64: 615 Ford Circle, Conway, SC 29526 | G64: 1501711033 | J64: waived | K64: 92861.3 | N64: =IF(OR(B64="",L64=""),"",MAX(0,B64-L64)) | O64: =IF(K64="","",K64+IF(OR(M64="",N64=""),0,M64*N64)) | R64: =IF(OR(Q64="",Q64=0,O64=""),"",O64/Q64) | Y64: open | AC64: 615 Ford Circle, Conway, SC 29526. Judgment $92,861.30. Deficiency waived — final on the day.
A65: Horry | B65: 46273 | D65: 2022-CP-26-05682 | E65: scheduled | F65: 4155 Heather Lakes Drive, Little River, SC 29566 | G65: 1183101012 | J65: waived | K65: 455702.77 | N65: =IF(OR(B65="",L65=""),"",MAX(0,B65-L65)) | O65: =IF(K65="","",K65+IF(OR(M65="",N65=""),0,M65*N65)) | R65: =IF(OR(Q65="",Q65=0,O65=""),"",O65/Q65) | Y65: open | AC65: 4155 Heather Lakes Drive, Little River, SC 29566. Judgment $455,702.77. Deficiency waived — final on the day.
A66: Horry | B66: 46273 | D66: 2025-CP-26-06064 | E66: scheduled | F66: 3526 Saint James Avenue, Myrtle Beach, SC 29577 | G66: 1732402077 | J66: waived | K66: 303355.55 | N66: =IF(OR(B66="",L66=""),"",MAX(0,B66-L66)) | O66: =IF(K66="","",K66+IF(OR(M66="",N66=""),0,M66*N66)) | R66: =IF(OR(Q66="",Q66=0,O66=""),"",O66/Q66) | Y66: open | AC66: 3526 Saint James Avenue, Myrtle Beach, SC 29577. Judgment $303,355.55. Deficiency waived — final on the day.
A67: Horry | B67: 46273 | D67: 2025-CP-26-07873 | E67: scheduled | F67: 1207 S Ocean Blvd, Unit 50613, Myrtle Beach, SC 29577 | G67: 1811302144 | J67: waived | K67: 19877.49 | N67: =IF(OR(B67="",L67=""),"",MAX(0,B67-L67)) | O67: =IF(K67="","",K67+IF(OR(M67="",N67=""),0,M67*N67)) | R67: =IF(OR(Q67="",Q67=0,O67=""),"",O67/Q67) | Y67: open | AC67: 1207 S Ocean Blvd, Unit 50613, Myrtle Beach, SC 29577. Judgment $19,877.49. Deficiency waived — final on the day.
A68: Horry | B68: 46273 | D68: 2026-CP-26-02340 | E68: scheduled | F68: 2001 S Ocean Blvd, Unit 203, Myrtle Beach, SC 29577 | G68: 1870108055 | J68: waived | K68: 146491 | N68: =IF(OR(B68="",L68=""),"",MAX(0,B68-L68)) | O68: =IF(K68="","",K68+IF(OR(M68="",N68=""),0,M68*N68)) | R68: =IF(OR(Q68="",Q68=0,O68=""),"",O68/Q68) | Y68: open | AC68: 2001 S Ocean Blvd, Unit 203, Myrtle Beach, SC 29577. Judgment $146,491.00. Deficiency waived — final on the day.
A69: Horry | B69: 46273 | D69: 2026-CP-26-01570 | E69: scheduled | F69: 709 Highway 90, Conway, SC 29526 | G69: 1380002005 | J69: waived | K69: 284997.41 | N69: =IF(OR(B69="",L69=""),"",MAX(0,B69-L69)) | O69: =IF(K69="","",K69+IF(OR(M69="",N69=""),0,M69*N69)) | R69: =IF(OR(Q69="",Q69=0,O69=""),"",O69/Q69) | Y69: open | AC69: 709 Highway 90, Conway, SC 29526. Judgment $284,997.41. Deficiency waived — final on the day.
A70: Horry | B70: 46273 | D70: 2012-CP-26-04357 | E70: scheduled | F70: 966 Willowbend Drive, Myrtle Beach, SC 29579 | G70: 1642201183 | J70: waived | K70: 589862.15 | N70: =IF(OR(B70="",L70=""),"",MAX(0,B70-L70)) | O70: =IF(K70="","",K70+IF(OR(M70="",N70=""),0,M70*N70)) | R70: =IF(OR(Q70="",Q70=0,O70=""),"",O70/Q70) | Y70: open | AC70: 966 Willowbend Drive, Myrtle Beach, SC 29579. Judgment $589,862.15. Deficiency waived — final on the day.
A71: Horry | B71: 46273 | D71: 2022-CP-26-05695 | E71: scheduled | F71: 4395 Bayberry Drive, Little River, SC 29566 | G71: 1302701056 | J71: waived | K71: 93632.2 | N71: =IF(OR(B71="",L71=""),"",MAX(0,B71-L71)) | O71: =IF(K71="","",K71+IF(OR(M71="",N71=""),0,M71*N71)) | R71: =IF(OR(Q71="",Q71=0,O71=""),"",O71/Q71) | Y71: open | AC71: 4395 Bayberry Drive, Little River, SC 29566. Judgment $93,632.20. Deficiency waived — final on the day.
A72: Horry | B72: 46273 | D72: 2026-CP-26-01007 | E72: scheduled | F72: 232 Waterfall Circle, Little River, SC 29566 | G72: 1303301099 | J72: waived | K72: 88145.75 | N72: =IF(OR(B72="",L72=""),"",MAX(0,B72-L72)) | O72: =IF(K72="","",K72+IF(OR(M72="",N72=""),0,M72*N72)) | R72: =IF(OR(Q72="",Q72=0,O72=""),"",O72/Q72) | Y72: open | AC72: 232 Waterfall Circle, Little River, SC 29566. Judgment $88,145.75. Deficiency waived — final on the day.
A73: Horry | B73: 46273 | D73: 2025-CP-26-02197 | E73: scheduled | F73: 3271 Lyndon Drive, Little River, SC 29566 | G73: 1301801078 | J73: waived | K73: 207547.1 | N73: =IF(OR(B73="",L73=""),"",MAX(0,B73-L73)) | O73: =IF(K73="","",K73+IF(OR(M73="",N73=""),0,M73*N73)) | R73: =IF(OR(Q73="",Q73=0,O73=""),"",O73/Q73) | Y73: open | AC73: 3271 Lyndon Drive, Little River, SC 29566. Judgment $207,547.10. Deficiency waived — final on the day.
A74: Horry | B74: 46273 | D74: 2025-CP-26-08959 | E74: scheduled | F74: 4242 Bonaire Lane, Little River, SC 29566 | J74: waived | K74: 196622.79 | N74: =IF(OR(B74="",L74=""),"",MAX(0,B74-L74)) | O74: =IF(K74="","",K74+IF(OR(M74="",N74=""),0,M74*N74)) | R74: =IF(OR(Q74="",Q74=0,O74=""),"",O74/Q74) | Y74: open | AC74: 4242 Bonaire Lane, Little River, SC 29566. Judgment $196,622.79. Deficiency waived — final on the day.
A75: Horry | B75: 46273 | D75: 2026-CP-26-02042 | E75: scheduled | F75: 1316 Tidway Circle, Conway, SC 29527 | G75: 1481901046 | J75: waived | K75: 92734.27 | N75: =IF(OR(B75="",L75=""),"",MAX(0,B75-L75)) | O75: =IF(K75="","",K75+IF(OR(M75="",N75=""),0,M75*N75)) | R75: =IF(OR(Q75="",Q75=0,O75=""),"",O75/Q75) | Y75: open | AC75: 1316 Tidway Circle, Conway, SC 29527. Judgment $92,734.27. Deficiency waived — final on the day.
A76: Horry | B76: 46273 | D76: 2026-CP-26-00192 | E76: scheduled | F76: 1505 Dunn Shortcut Road, Conway, SC 29527 | G76: 1210003058 | J76: waived | K76: 238913.77 | N76: =IF(OR(B76="",L76=""),"",MAX(0,B76-L76)) | O76: =IF(K76="","",K76+IF(OR(M76="",N76=""),0,M76*N76)) | R76: =IF(OR(Q76="",Q76=0,O76=""),"",O76/Q76) | Y76: open | AC76: 1505 Dunn Shortcut Road, Conway, SC 29527. Judgment $238,913.77. Deficiency waived — final on the day.
A77: Pickens | B77: 46273 | C77: 1 | D77: 2025-CP-39-01688 | E77: cancelled | F77: 443 MARY ANN ST., EASLEY, SC 29640 | G77: 5110-18-40-1736 | H77: FINANCE OF AMERICA REVERSE, LLC | I77: ESTATE OF PATRICIA TUCKER CAPPS, ET AL | J77: unknown | N77: =IF(OR(B77="",L77=""),"",MAX(0,B77-L77)) | O77: =IF(K77="","",K77+IF(OR(M77="",N77=""),0,M77*N77)) | R77: =IF(OR(Q77="",Q77=0,O77=""),"",O77/Q77) | AC77: 443 MARY ANN ST., EASLEY, SC 29640. Judgment $ not pulled yet (needs the PC run). Deficiency not stated — check the notice. STATUS: CANCELLED.
A78: Pickens | B78: 46273 | C78: 2 | D78: 2024-CP-39-00316 | E78: scheduled | F78: 103 WINDAMERE CT., EASLEY, SC 29640 | G78: 5110-20-82-3366 | H78: US BANK TRUST NA | I78: HEATHER HOWELL, PR, ET AL | J78: unknown | N78: =IF(OR(B78="",L78=""),"",MAX(0,B78-L78)) | O78: =IF(K78="","",K78+IF(OR(M78="",N78=""),0,M78*N78)) | R78: =IF(OR(Q78="",Q78=0,O78=""),"",O78/Q78) | AC78: 103 WINDAMERE CT., EASLEY, SC 29640. Judgment $ not pulled yet (needs the PC run). Deficiency not stated — check the notice.
A79: Pickens | B79: 46273 | C79: 3 | D79: 2018-CP-39-00369 | E79: scheduled | F79: 649 N. NORRIS DR., LIBERTY, SC 29657 | G79: 4077-15-62-1769 | H79: NATIONSTAR MORTGAGE LLC DBA MR. COOPER | I79: JENNIFER RENEE KEPHART, ET AL | J79: unknown | N79: =IF(OR(B79="",L79=""),"",MAX(0,B79-L79)) | O79: =IF(K79="","",K79+IF(OR(M79="",N79=""),0,M79*N79)) | R79: =IF(OR(Q79="",Q79=0,O79=""),"",O79/Q79) | AC79: 649 N. NORRIS DR., LIBERTY, SC 29657. Judgment $ not pulled yet (needs the PC run). Deficiency not stated — check the notice.
A80: Pickens | B80: 46273 | C80: 4 | D80: 2026-CP-39-00125 | E80: scheduled | F80: 365 GIBSON RD., EASLEY, SC 29640 | G80: 5111-01-47-3602 | H80: LAKEVIEW LOAN SERVICING LLC | I80: NICOLE MARIA JACOBS, ET AL | J80: unknown | N80: =IF(OR(B80="",L80=""),"",MAX(0,B80-L80)) | O80: =IF(K80="","",K80+IF(OR(M80="",N80=""),0,M80*N80)) | R80: =IF(OR(Q80="",Q80=0,O80=""),"",O80/Q80) | AC80: 365 GIBSON RD., EASLEY, SC 29640. Judgment $ not pulled yet (needs the PC run). Deficiency not stated — check the notice.
A81: Pickens | B81: 46273 | C81: 5 | D81: 2026-CP-39-00009 | E81: cancelled | F81: 105 SPIRIT MOUNTAIN LN., EASLEY, SC 29642 | G81: 5018-11-57-8000 | H81: UNITED COMMUNITY BANK | I81: THE TOPAZ GROUP LLC DBA AMICI ITALIAN CAFÉ, ET AL | J81: demanded | N81: =IF(OR(B81="",L81=""),"",MAX(0,B81-L81)) | O81: =IF(K81="","",K81+IF(OR(M81="",N81=""),0,M81*N81)) | R81: =IF(OR(Q81="",Q81=0,O81=""),"",O81/Q81) | AC81: 105 SPIRIT MOUNTAIN LN., EASLEY, SC 29642. Judgment $ not pulled yet (needs the PC run). DEFICIENCY DEMANDED — open 30 days (reopens OCTOBER 8, 2026). STATUS: CANCELLED.
A82: Pickens | B82: 46273 | C82: 6 | D82: 2025-CP-39-01333 | E82: cancelled | F82: 220 AMSTERDAM RD., LIBERTY, SC 29657 | G82: 5008-10-46-2969 | H82: LAKEVIEW LOAN SERVICING, LLC | I82: RYAN L. GOLDEN, ET AL | J82: unknown | N82: =IF(OR(B82="",L82=""),"",MAX(0,B82-L82)) | O82: =IF(K82="","",K82+IF(OR(M82="",N82=""),0,M82*N82)) | R82: =IF(OR(Q82="",Q82=0,O82=""),"",O82/Q82) | AC82: 220 AMSTERDAM RD., LIBERTY, SC 29657. Judgment $ not pulled yet (needs the PC run). Deficiency not stated — check the notice. STATUS: CANCELLED.
A83: Pickens | B83: 46273 | C83: 7 | D83: 2024-CP-39-00803 | E83: scheduled | F83: 115 BLUE SKY DR., SUNSET, SC 29685 | G83: 4164-00-68-4910 | H83: LEGACY FACTORY DIRECT HOMES, LLC | I83: TIMOTHY R. BUTLER, ET AL | J83: unknown | N83: =IF(OR(B83="",L83=""),"",MAX(0,B83-L83)) | O83: =IF(K83="","",K83+IF(OR(M83="",N83=""),0,M83*N83)) | R83: =IF(OR(Q83="",Q83=0,O83=""),"",O83/Q83) | AC83: 115 BLUE SKY DR., SUNSET, SC 29685. Judgment $ not pulled yet (needs the PC run). Deficiency not stated — check the notice.
A84: Spartanburg | B84: 46273 | D84: 2023-CP-42-01464 | E84: scheduled | F84: 142 Birkdale Drive Spartanburg, SC 29306 | G84: 6-35-00-308.00 | H84: U.S. Bank Trust National Association, not in its individual capacity but solely as owner trustee for RCAF Acquisition Trust | I84: Carole W Messer a/k/a Carole W Wofford; South Carolina Department of Revenue; The Carolina Country Club Real Estate Owners Association | J84: demanded | N84: =IF(OR(B84="",L84=""),"",MAX(0,B84-L84)) | O84: =IF(K84="","",K84+IF(OR(M84="",N84=""),0,M84*N84)) | P84: 3.5% | R84: =IF(OR(Q84="",Q84=0,O84=""),"",O84/Q84) | Z84: open | AC84: 142 Birkdale Drive Spartanburg, SC 29306. Judgment $ not pulled yet (needs the PC run). DEFICIENCY DEMANDED — open 30 days. Interest on bid 3.5% until compliance; 5% deposit day of sale.
A85: Spartanburg | B85: 46273 | D85: 2026-CP-42-01692 | E85: scheduled | F85: 1172 Maryland Avenue Spartanburg, SC 29307 | G85: 7-09-13-070.01 | H85: Wilmington Savings Fund Society, FSB, not in its individual capacity but solely as Owner Trustee for the FLIC Residential Mortgage Loan Trust 1 | I85: VSWC, LLC; Willie Coleman; Daniel Dsouza | J85: waived | N85: =IF(OR(B85="",L85=""),"",MAX(0,B85-L85)) | O85: =IF(K85="","",K85+IF(OR(M85="",N85=""),0,M85*N85)) | P85: 7% | R85: =IF(OR(Q85="",Q85=0,O85=""),"",O85/Q85) | Z85: open | AC85: 1172 Maryland Avenue Spartanburg, SC 29307. Judgment $ not pulled yet (needs the PC run). Deficiency waived — final on the day. Interest on bid 7% until compliance; 5% deposit day of sale.
A86: Spartanburg | B86: 46273 | D86: 2026-CP-42-01301 | E86: scheduled | F86: 1269 Kilead Court Boiling Springs, SC 29316 | G86: 2-51-00-018.08 | H86: MidFirst Bank | I86: Kaitlyn Weathers; Austin Weathers; B5 RE Investments LLC; Standing Rock Homeowners Association | J86: waived | N86: =IF(OR(B86="",L86=""),"",MAX(0,B86-L86)) | O86: =IF(K86="","",K86+IF(OR(M86="",N86=""),0,M86*N86)) | P86: 7.125% | R86: =IF(OR(Q86="",Q86=0,O86=""),"",O86/Q86) | Z86: open | AC86: 1269 Kilead Court Boiling Springs, SC 29316. Judgment $ not pulled yet (needs the PC run). Deficiency waived — final on the day. Interest on bid 7.125% until compliance; 5% deposit day of sale.
A87: Spartanburg | B87: 46273 | D87: 2025-CP-42-05920 | E87: scheduled | F87: 62 Woodwind Drive Spartanburg, SC 29302 | G87: 7-21-13-021.00 | H87: Lakeview Loan Servicing, LLC | I87: Laky Yang; Thomas W. Hoelscher; Wendy B. Hoelscher | J87: waived | N87: =IF(OR(B87="",L87=""),"",MAX(0,B87-L87)) | O87: =IF(K87="","",K87+IF(OR(M87="",N87=""),0,M87*N87)) | P87: 4.99% | R87: =IF(OR(Q87="",Q87=0,O87=""),"",O87/Q87) | Z87: open | AC87: 62 Woodwind Drive Spartanburg, SC 29302. Judgment $ not pulled yet (needs the PC run). Deficiency waived — final on the day. Interest on bid 4.99% until compliance; 5% deposit day of sale.
A88: Spartanburg | B88: 46273 | D88: 2025-CP-42-04034 | E88: scheduled | F88: 109 Nevada Street, Spartanburg, SC 29306 | G88: 7-16-07-130.10 | H88: U.S. Bank Trust Company, National Association, as Trustee, as successor-in-interest to U.S. Bank National Association, not in its individual capacity but solely as indenture trustee, for the holders of the CIM Trust 2021-R5, Mortgage-Backed Notes, Series 2021-R5 | I88: Any heirs-at-law or devisees of Bobby J. Davis a/k/a Bobby Joe Davis, Sr., deceased, their heirs, Personal Representatives, Administrators, Successors and Assigns, and all other persons or entities entitled to claim through them; all unknown persons or entities with any right, title, estate, interest in or lien upon the real estate described in the complaint herein; also any persons who may be in the military service of the United States of America, being a class designated as Richard Roe; and any unknown minors, incompetent or imprisoned person, or persons under a disability being a class designated as John Doe; Donna Davis; Michelle Darlene Davis; Shawn N. Cooper; Bobby Joe Davis, Jr.; Charles L. Davis; Michael Burch | J88: waived | N88: =IF(OR(B88="",L88=""),"",MAX(0,B88-L88)) | O88: =IF(K88="","",K88+IF(OR(M88="",N88=""),0,M88*N88)) | R88: =IF(OR(Q88="",Q88=0,O88=""),"",O88/Q88) | Z88: open | AC88: 109 Nevada Street, Spartanburg, SC 29306. Judgment $ not pulled yet (needs the PC run). Deficiency waived — final on the day.
A89: Spartanburg | B89: 46273 | D89: 2025-CP-42-05179 | E89: scheduled | F89: 353 Honor Road, Duncan, SC 29334 | G89: 5-19-00-356.00 | H89: Wells Fargo Bank, N.A. | I89: Any heirs-at-law or devisees of Brian P. Gilchrest, deceased, their heirs, Personal Representatives, Administrators, Successors and Assigns, and all other persons or entities entitled to claim through them; all unknown persons or entities with any right, title, estate, interest in or lien upon the real estate described in the complaint herein; also any persons who may be in the military service of the United States of America, being a class designated as Richard Roe; and any unknown minors, incompetent or imprisoned person, or persons under a disability being a class designated as John Doe; Robin Baker Gilchrest; Brian Henry Gilchrest; Elaine Marie Gilchrest; Z.L.G.(minor); The United States of America, acting by and through its Agency, The Secretary of Housing and Urban Development | J89: waived | N89: =IF(OR(B89="",L89=""),"",MAX(0,B89-L89)) | O89: =IF(K89="","",K89+IF(OR(M89="",N89=""),0,M89*N89)) | R89: =IF(OR(Q89="",Q89=0,O89=""),"",O89/Q89) | Z89: open | AC89: 353 Honor Road, Duncan, SC 29334. Judgment $ not pulled yet (needs the PC run). Deficiency waived — final on the day. USA right of redemption applies (federal lien).
A90: Spartanburg | B90: 46273 | D90: 2025-CP-42-05042 | E90: scheduled | F90: 155 Nesbitt Road, Wellford, SC 29385 | G90: 5-16-13-044.00 | H90: Fifth Third Bank N.A. | I90: Pamela Y. Pettigrew a/k/a Pamela Y. Lynch; The United States of America, acting by and through its Agency, The Secretary of Housing and Urban Development | J90: demanded | N90: =IF(OR(B90="",L90=""),"",MAX(0,B90-L90)) | O90: =IF(K90="","",K90+IF(OR(M90="",N90=""),0,M90*N90)) | R90: =IF(OR(Q90="",Q90=0,O90=""),"",O90/Q90) | Z90: open | AC90: 155 Nesbitt Road, Wellford, SC 29385. Judgment $ not pulled yet (needs the PC run). DEFICIENCY DEMANDED — open 30 days. USA right of redemption applies (federal lien).
A91: Spartanburg | B91: 46273 | D91: 2025-CP-42-05438 | E91: scheduled | F91: 591 Stagecoach Road, Pauline, SC 29374 | G91: 6-62-00-035.03 | H91: Wells Fargo Bank, N.A. | I91: David W. Teaster; The United States of America, acting by and through its Agency, The Secretary of Housing and Urban Development | J91: waived | N91: =IF(OR(B91="",L91=""),"",MAX(0,B91-L91)) | O91: =IF(K91="","",K91+IF(OR(M91="",N91=""),0,M91*N91)) | R91: =IF(OR(Q91="",Q91=0,O91=""),"",O91/Q91) | Z91: open | AC91: 591 Stagecoach Road, Pauline, SC 29374. Judgment $ not pulled yet (needs the PC run). Deficiency waived — final on the day. USA right of redemption applies (federal lien).
A92: Spartanburg | B92: 46273 | D92: 2026-CP-42-01627 | E92: scheduled | F92: 102 Sparrow Ct, Boiling Springs, SC 29316 | G92: 2-44-00-067.01 | H92: Wells Fargo Bank, National Association as Trustee for Structured Asset Securities Corporation, Mortgage Pass-Through Certificates, Series 2006-OPT1 | I92: Choeun Chan a/k/a Cindy Chan; Nem Chan; Financial Trust, Inc.; 1st Franklin Financial Corporation | J92: demanded | N92: =IF(OR(B92="",L92=""),"",MAX(0,B92-L92)) | O92: =IF(K92="","",K92+IF(OR(M92="",N92=""),0,M92*N92)) | R92: =IF(OR(Q92="",Q92=0,O92=""),"",O92/Q92) | Z92: open | AC92: 102 Sparrow Ct, Boiling Springs, SC 29316. Judgment $ not pulled yet (needs the PC run). DEFICIENCY DEMANDED — open 30 days.
A93: Spartanburg | B93: 46273 | D93: 2025-CP-42-04289 | E93: scheduled | F93: 251 Longmont Drive, Boiling Springs, SC 29316 | G93: 2-37-00-051.75 | H93: Lakeview Loan Servicing, LLC | I93: Racquel Nicole Lynch a/k/a Racquel Lynch; The United States of America, acting by and through its Agency, The Secretary of Housing and Urban Development; Republic Finance, LLC; Rolands Crossing Homeowners Association, Inc. | J93: waived | N93: =IF(OR(B93="",L93=""),"",MAX(0,B93-L93)) | O93: =IF(K93="","",K93+IF(OR(M93="",N93=""),0,M93*N93)) | R93: =IF(OR(Q93="",Q93=0,O93=""),"",O93/Q93) | Z93: open | AC93: 251 Longmont Drive, Boiling Springs, SC 29316. Judgment $ not pulled yet (needs the PC run). Deficiency waived — final on the day. USA right of redemption applies (federal lien).
A94: Spartanburg | B94: 46273 | D94: 2026-CP-42-00897 | E94: scheduled | F94: 111 Goodlett St, Pacolet, SC 29372 | G94: 3-30-01-054.00 | H94: PennyMac Loan Services, LLC | I94: Jacob Shore | J94: waived | N94: =IF(OR(B94="",L94=""),"",MAX(0,B94-L94)) | O94: =IF(K94="","",K94+IF(OR(M94="",N94=""),0,M94*N94)) | R94: =IF(OR(Q94="",Q94=0,O94=""),"",O94/Q94) | Z94: open | AC94: 111 Goodlett St, Pacolet, SC 29372. Judgment $ not pulled yet (needs the PC run). Deficiency waived — final on the day.
A95: Spartanburg | B95: 46273 | D95: 2026-CP-42-01739 | E95: scheduled | F95: 1032 Longstone Way, Spartanburg, SC 29306 | G95: 7-21-00-058.09 | H95: Village Capital & Investment LLC | I95: Franklin S. Porter; Sylvia E. Porter; Hawthorn Grove Homeowners' Association, Inc.; Mortgage Electronic Registration Systems, Inc., as mortgagee, as nominee for Guaranteed Rate, Inc. | J95: waived | N95: =IF(OR(B95="",L95=""),"",MAX(0,B95-L95)) | O95: =IF(K95="","",K95+IF(OR(M95="",N95=""),0,M95*N95)) | R95: =IF(OR(Q95="",Q95=0,O95=""),"",O95/Q95) | Z95: open | AC95: 1032 Longstone Way, Spartanburg, SC 29306. Judgment $ not pulled yet (needs the PC run). Deficiency waived — final on the day.
A96: Spartanburg | B96: 46273 | D96: 2026-CP-42-01891 | E96: scheduled | F96: 4456 Duparc Way, Spartanburg, SC 29307 | G96: 7-05-00-201.19 | H96: Freedom Mortgage Corporation | I96: Kaden Darrin Morrell; Amanda Maria Morrell; Berkeley Homeowners' Association, Inc. | J96: waived | N96: =IF(OR(B96="",L96=""),"",MAX(0,B96-L96)) | O96: =IF(K96="","",K96+IF(OR(M96="",N96=""),0,M96*N96)) | R96: =IF(OR(Q96="",Q96=0,O96=""),"",O96/Q96) | Z96: open | AC96: 4456 Duparc Way, Spartanburg, SC 29307. Judgment $ not pulled yet (needs the PC run). Deficiency waived — final on the day.
A97: Spartanburg | B97: 46273 | D97: 2026-CP-42-00714 | E97: scheduled | F97: 686 California Avenue, Spartanburg, SC 29303 | G97: 6-13-08-155.00 | H97: Katline Realty Corp., LLC | I97: Malibu Real Estate Investments, LLC | J97: conflicting | N97: =IF(OR(B97="",L97=""),"",MAX(0,B97-L97)) | O97: =IF(K97="","",K97+IF(OR(M97="",N97=""),0,M97*N97)) | P97: 0% | R97: =IF(OR(Q97="",Q97=0,O97=""),"",O97/Q97) | Z97: open | AC97: 686 California Avenue, Spartanburg, SC 29303. Judgment $ not pulled yet (needs the PC run). DEFICIENCY LANGUAGE CONFLICTS in the notice (says both waived and open 30 days) — ask plaintiff's counsel: W: No personal or deficiency judgment being demanded, the bidding will not remain open after the date of sale, but compliance with the bid must be made immediately. | D: DEFICIENCY JUDGMENT IS PRESERVED AND THE BID WILL REMAIN OPEN FOR THIRTY DAYS. Interest on bid 0% until compliance; 5% deposit day of sale.
A98: Spartanburg | B98: 46273 | D98: 2026-CP-42-01014 | E98: scheduled | F98: 143 Woodhaven Drive, Spartanburg, SC 29307 | G98: 7-10-02-040.00 | H98: Pinnacle Bank d/b/a Synovus Bank | I98: Lasundra Danielle Williams; and Service Finance Company, LLC | J98: demanded | N98: =IF(OR(B98="",L98=""),"",MAX(0,B98-L98)) | O98: =IF(K98="","",K98+IF(OR(M98="",N98=""),0,M98*N98)) | R98: =IF(OR(Q98="",Q98=0,O98=""),"",O98/Q98) | Z98: open | AC98: 143 Woodhaven Drive, Spartanburg, SC 29307. Judgment $ not pulled yet (needs the PC run). DEFICIENCY DEMANDED — open 30 days.
A99: Spartanburg | B99: 46273 | D99: 2025-CP-42-02677 | E99: scheduled | F99: 324 Courson Court Boiling Springs, South Carolina 29316 | G99: 2-45-06-014.00 | H99: South Carolina State Housing Finance and Development Authority | I99: Natalie McKelvin et al | J99: waived | N99: =IF(OR(B99="",L99=""),"",MAX(0,B99-L99)) | O99: =IF(K99="","",K99+IF(OR(M99="",N99=""),0,M99*N99)) | R99: =IF(OR(Q99="",Q99=0,O99=""),"",O99/Q99) | Z99: open | AC99: 324 Courson Court Boiling Springs, South Carolina 29316. Judgment $ not pulled yet (needs the PC run). Deficiency waived — final on the day.
A100: Spartanburg | B100: 46273 | D100: 2025-CP-42-03885 | E100: scheduled | F100: 179 Briarcliff Road, Spartanburg, SC 29301 | G100: 7-15-08-100.00 | H100: Planet Home Lending, LLC | I100: Jakira Bogan a/k/a Jakira A. Bogan; Correy T. Bogan; Derrick B. Bogan a/k/a Derrick Bernard Bogan; et.al. | J100: demanded | N100: =IF(OR(B100="",L100=""),"",MAX(0,B100-L100)) | O100: =IF(K100="","",K100+IF(OR(M100="",N100=""),0,M100*N100)) | R100: =IF(OR(Q100="",Q100=0,O100=""),"",O100/Q100) | Z100: open | AC100: 179 Briarcliff Road, Spartanburg, SC 29301. Judgment $ not pulled yet (needs the PC run). DEFICIENCY DEMANDED — open 30 days.
A101: Spartanburg | B101: 46273 | D101: 2025-CP-42-05868 | E101: scheduled | F101: 111 Whitener Avenue, Spartanburg, SC 29306 | G101: 7-16-12-031.00 | H101: U.S. Bank Trust National Association, not in its individual capacity but solely as owner trustee for Legacy Mortgage Asset Trust 2024-INV1 | I101: HGMCV1 LLC | J101: demanded | N101: =IF(OR(B101="",L101=""),"",MAX(0,B101-L101)) | O101: =IF(K101="","",K101+IF(OR(M101="",N101=""),0,M101*N101)) | R101: =IF(OR(Q101="",Q101=0,O101=""),"",O101/Q101) | Z101: open | AC101: 111 Whitener Avenue, Spartanburg, SC 29306. Judgment $ not pulled yet (needs the PC run). DEFICIENCY DEMANDED — open 30 days.
A102: Spartanburg | B102: 46273 | D102: 2025-CP-42-00105 | E102: scheduled | F102: 116 Carolyn Drive, Spartanburg, SC 29306 | G102: 7-16-12-026.00 | H102: U.S. Bank Trust National Association, not in its individual capacity but solely as owner trustee for GS Mortgage-Backed Securities Trust 2022-RPL2 | I102: Theresa Jackson Miller a/k/a Theresa Miller, as Heir or Devisee of the Estate of James Roosevelt Jackson a/k/a James R. Jackson a/k/a James Jackson, Deceased; Doris Davis, as Heir or Devisee of the Estate of James Roosevelt Jackson a/k/a James R. Jackson a/k/a James Jackson, Deceased; et.al. | J102: waived | N102: =IF(OR(B102="",L102=""),"",MAX(0,B102-L102)) | O102: =IF(K102="","",K102+IF(OR(M102="",N102=""),0,M102*N102)) | R102: =IF(OR(Q102="",Q102=0,O102=""),"",O102/Q102) | Z102: open | AC102: 116 Carolyn Drive, Spartanburg, SC 29306. Judgment $ not pulled yet (needs the PC run). Deficiency waived — final on the day.
A103: Spartanburg | B103: 46273 | D103: 2026-CP-42-00672 | E103: scheduled | F103: 112 Mt Lebanon Road, Pauline, SC 29374 | G103: 6-63-00-005.07 | H103: JPMorgan Chase Bank, National Association | I103: Linda Lawter; and Susan Lawter | J103: waived | N103: =IF(OR(B103="",L103=""),"",MAX(0,B103-L103)) | O103: =IF(K103="","",K103+IF(OR(M103="",N103=""),0,M103*N103)) | R103: =IF(OR(Q103="",Q103=0,O103=""),"",O103/Q103) | Z103: open | AC103: 112 Mt Lebanon Road, Pauline, SC 29374. Judgment $ not pulled yet (needs the PC run). Deficiency waived — final on the day.
A104: Spartanburg | B104: 46273 | D104: 2026-CP-42-01993 | E104: scheduled | F104: 229 Cherokee Circle, Spartanburg, SC 29307 | G104: 2-46-00-003.00 | H104: U.S. Bank Trust National Association, not in its individual capacity but solely as owner trustee for Legacy Mortgage Asset Trust 2021-GS2 | I104: Helen Louise Long a/k/a Helen L. Long; Johnny Thomas Long; Michael Alan Long a/k/a Michael Long, and if he be deceased, et.al. | J104: waived | N104: =IF(OR(B104="",L104=""),"",MAX(0,B104-L104)) | O104: =IF(K104="","",K104+IF(OR(M104="",N104=""),0,M104*N104)) | R104: =IF(OR(Q104="",Q104=0,O104=""),"",O104/Q104) | Z104: open | AC104: 229 Cherokee Circle, Spartanburg, SC 29307. Judgment $ not pulled yet (needs the PC run). Deficiency waived — final on the day.
A105: Spartanburg | B105: 46273 | D105: 2018-CP-42-02911 | E105: scheduled | F105: 225 Rexford Drive, Moore, SC 29369 | G105: 5-32-00-528.00 | H105: FirstBank | I105: Terri Rookard; et.al. | J105: waived | N105: =IF(OR(B105="",L105=""),"",MAX(0,B105-L105)) | O105: =IF(K105="","",K105+IF(OR(M105="",N105=""),0,M105*N105)) | R105: =IF(OR(Q105="",Q105=0,O105=""),"",O105/Q105) | Z105: open | AC105: 225 Rexford Drive, Moore, SC 29369. Judgment $ not pulled yet (needs the PC run). Deficiency waived — final on the day.
A106: Spartanburg | B106: 46273 | D106: 2025-CP-42-06354 | E106: scheduled | F106: 135 Knollwood Drive, Spartanburg, SC 29301 | G106: 6-21-13-099.00 | H106: NewRez LLC d/b/a Shellpoint Mortgage Servicing | I106: Ta'Jio D. Reeves | J106: waived | N106: =IF(OR(B106="",L106=""),"",MAX(0,B106-L106)) | O106: =IF(K106="","",K106+IF(OR(M106="",N106=""),0,M106*N106)) | R106: =IF(OR(Q106="",Q106=0,O106=""),"",O106/Q106) | Z106: open | AC106: 135 Knollwood Drive, Spartanburg, SC 29301. Judgment $ not pulled yet (needs the PC run). Deficiency waived — final on the day.
...

Sheet Sale calendar
A1: County | B1: Sale day rule | C1: Time | D1: Location | E1: Next dates | F1: Notes
A2: Greenville | B2: 1st Monday (Tue if holiday) | C2: 11:00 AM | D2: Greenville County Courthouse, 305 E North St, judicial wing | E2: Sep 8 · Oct 5 · Nov 2 · Dec 7 2026 | F2: 5% deposit; deficiency re-bid day 30 (Oct 8 for the Sept sale)
A3: Pickens | B3: 1st Monday (Tue if holiday) | C3: 11:00 AM | D3: Pickens County Courthouse, 2nd floor, Courtroom #1 | E3: Sep 8 · Oct 5 · Nov 2 · Dec 7 2026 | F3: Deficiency re-bid Oct 8 2026 11:00 AM, Courtroom #4 or #2
A4: Spartanburg | B4: 1st Monday (Tue if holiday) | C4: 11:00 AM | D4: 180 Magnolia St, 4th floor, Courtroom 4-A | E4: Sep 8 · Oct 5 · Nov 2 · Dec 7 2026 | F4: Deficiency sales ~30 days later (county posts a Deficiency Sale doc)
A5: Oconee | B5: 1st Monday (Tue if holiday) | C5: 11:00 AM | D5: Oconee County Courthouse, Walhalla | E5: Sep 8 · Oct 5 · Nov 2 · Dec 7 2026 | F5: List on the SC Public Index roster (Master In Equity)
A6: Horry | B6: 1st Monday (Tue if holiday) | C6: 11:00 AM | D6: 1301 2nd Ave, 3rd floor, Conway | E6: Sep 8 · Oct 5 · Nov 2 · Dec 7 2026 | F6: New bidders register 7 days ahead; first-time winners bring $2,500 certified
A7: Charleston | B7: 1st TUESDAY | C7: 11:00 AM | D7: County Council Chambers, PSB, 4045 Bridge View Dr, N. Charleston | E7: Oct 6 · Nov 3 · Dec 1 2026 | F7: REGISTER by noon the Monday before (form + photo ID); re-open sales Thursdays at 100 Broad St, Courtroom 2A
A8: Georgetown | B8: 1st Monday | C8: 12:00 NOON | D8: 401 Cleland St, 2nd floor MIE courtroom | E8: Sep 8 (confirm) · Oct 5 · Nov 2 · Dec 7 2026 | F8: Holiday rule is "next day or next Monday" – confirm September (843-546-3103)
A9: Beaufort | B9: 1st Monday (next business day if holiday) | C9: 11:00 AM | D9: 102 Ribaut Rd, 2nd floor, Beaufort | E9: Sep 8 · Oct 5 · Nov 2 · Dec 7 2026 | F9: List: notebook outside MIE office + Public Index roster
A10: Berkeley | B10: 1st WEDNESDAY | C10: 11:00 AM | D10: Courtroom B, 300-B California Ave, Moncks Corner | E10: Oct 7 · Nov 4 · Dec 2 2026 | F10: MIE (843) 719-4432
A11: Dorchester | B11: UNVERIFIED – assumed 1st Monday | C11: 11:00 AM (assumed) | D11: St. George courthouse | E11: Oct 5 · Nov 2 · Dec 7 2026 (confirm) | F11: Confirm with Clerk (843) 563-0120
A12: Colleton | B12: UNVERIFIED – assumed 1st Monday | C12: 11:00 AM (assumed) | D12: Walterboro courthouse | E12: Oct 5 · Nov 2 · Dec 7 2026 (confirm) | F12: Confirm with Clerk (843) 549-5791

Sheet Read me
A1: How to read this workbook
A2: Judgment $ = the total the court entered (Order of Foreclosure / Form 4). Horry and Charleston publish it on their sale lists; other counties need the court-index run from Brian's PC (tools/foreclosures in the hello-world repo).
A3: Est. owed sale day = Judgment $ + per diem × days between the as-of date and the sale. This is the plaintiff's credit-bid ceiling, not the opening bid.
A4: Deficiency demanded = bidding stays open 30 days; anyone can top the day-of bid at the re-open. Waived = sale is final that day. "conflicting" = the notice says both; call plaintiff's counsel.
A5: Debt ÷ FMV under ~70% = real equity, expect competition; over 100% = plaintiff likely takes it back.
A6: County FMV / owner / acreage come from the county property card (Greenville live; qPublic counties need the PC run).
A7: Source of each row: Greenville = MIE sale list PDF (transcribed); Pickens = county roster PDF; Spartanburg = Spartan Weekly notices; Horry = county Principal Sales page; Georgetown = county DocumentCenter list; Charleston = Master's running list.
A8: Generated 2026-09-08 by tools/foreclosures/scripts/build-xlsx.py.
